{"authors_arexon_index.md":"e64e49c3","authors_braden_index.md":"57a85fa7","authors_cubed-creations_index.md":"36e5c2cb","authors_drp_index.md":"ddb694e7","authors_gamemode-one_index.md":"6830c6b3","authors_kekecreations_index.md":"4710c33f","authors_mcjiprock_index.md":"59ad1c7f","authors_spectral-studios_index.md":"c45d2d11","authors_xxpoggyislitxx_index.md":"192f5de9","creations_advanced-mining_index.md":"5f2be1be","creations_blood-rot_index.md":"ead74c05","creations_bloom_index.md":"74d03549","creations_dragon-fire-2_index.md":"bb9c94bf","creations_dragon-fire_index.md":"bfdc9b05","creations_elemental-weapons_index.md":"f2478280","creations_furnideco_index.md":"644085bc","creations_high-and-dry_index.md":"9f74acb3","creations_httyd_index.md":"4e123ffe","creations_index.md":"991daec9","creations_pac-man_index.md":"23c27cf6","creations_planes_index.md":"ce3a6d1d","creations_seaside-story_index.md":"210c3c1f","creations_sonic_index.md":"75d2385a","creations_spellcraft_index.md":"30dc25eb","creations_the-corruption_index.md":"4969175a","creations_ultimate-dragons_index.md":"96a21e29","creations_voidlands-dimensions_index.md":"8b6bd71d","creations_world-against_index.md":"bef78f14","creations_world-is-quite-literally-your-enemy_index.md":"ea161385","extensions_compiler-plugins.md":"7bbdc6a0","extensions_contributing.md":"bed481cc","extensions_extension-manifest.md":"fb76b17d","extensions_iframe-api_index.md":"24953932","extensions_index.md":"768227fc","extensions_json_file-definitions.md":"3018fefc","extensions_json_lightning-cache.md":"109eae45","extensions_json_themes.md":"14f0161d","extensions_misc_file-types.md":"c0431dcc","extensions_misc_icons_index.md":"88685336","extensions_misc_pack-types.md":"a376caaf","extensions_presets_index.md":"d2984d7e","extensions_presets_manifest_index.md":"1d4f38ec","extensions_presets_preset-scripts.md":"32de8f4a","extensions_publishing_components-and-commands.md":"5368048e","extensions_publishing_index.md":"4d01f87a","extensions_scripts_index.md":"3d6aaf62","extensions_snippets_documentation.md":"a0688178","extensions_snippets_index.md":"3c8acd05","guide_advanced_custom-commands_index.md":"52a61e1a","guide_advanced_custom-components_index.md":"e7c86989","guide_advanced_dash_index.md":"c6453ea0","guide_advanced_generator-scripts_index.md":"edd857bf","guide_advanced_molang-ast-scripts_index.md":"c89d30ca","guide_advanced_molang-files_index.md":"a2903bb5","guide_community.md":"028ccdcd","guide_download_index.md":"010a4e8c","guide_faq_index.md":"e6943ae1","guide_features_index.md":"023105ea","guide_index.md":"d57b30bf","guide_migration-guide_index.md":"02eb88db","guide_misc_com-mojang-syncing_index.md":"d720d61f","guide_misc_export-project_index.md":"3de90681","guide_misc_import-project.md":"209025a6","guide_misc_project-config.md":"23c6f387","guide_misc_project-types_index.md":"a6ce620b","guide_why-bridge.md":"734ce8a9","index.md":"4cf357ac","team.md":"b20d54ed"}
