{"authors_arexon_index.md":"ef64c239","authors_braden_index.md":"3e1b53d3","authors_cubed-creations_index.md":"70c1a9c9","authors_drp_index.md":"2d51a0e1","authors_gamemode-one_index.md":"d239ce35","authors_kekecreations_index.md":"fb7b498d","authors_mcjiprock_index.md":"93c3c53b","authors_spectral-studios_index.md":"be3c4d48","authors_xxpoggyislitxx_index.md":"f17ff57f","creations_advanced-mining_index.md":"30c64c94","creations_blood-rot_index.md":"65adedd7","creations_bloom_index.md":"fc8dcdcf","creations_dragon-fire-2_index.md":"a4fe7cdb","creations_dragon-fire_index.md":"786ff6f1","creations_elemental-weapons_index.md":"602aed46","creations_furnideco_index.md":"07587692","creations_high-and-dry_index.md":"176dfb58","creations_httyd_index.md":"a0067277","creations_index.md":"e5976d8a","creations_overpowered-wands_index.md":"5a03a374","creations_pac-man_index.md":"db962aa2","creations_planes_index.md":"dd6ca968","creations_scifi-weapons_index.md":"1f0e460d","creations_seaside-story_index.md":"38b10fe7","creations_sonic_index.md":"b38ad32b","creations_spellcraft_index.md":"cc213bda","creations_the-corruption_index.md":"aef7d652","creations_ultimate-dragons_index.md":"127eb017","creations_voidlands-dimensions_index.md":"17badeaf","creations_world-against_index.md":"1268d809","creations_world-is-quite-literally-your-enemy_index.md":"149f4c51","extensions_compiler-plugins.md":"b2f7bfab","extensions_contributing.md":"3506a497","extensions_extension-manifest.md":"da651c77","extensions_iframe-api_index.md":"c7fb3f6a","extensions_index.md":"6e1753d8","extensions_json_file-definitions.md":"551a6529","extensions_json_lightning-cache.md":"2a1175ea","extensions_json_themes.md":"215cb093","extensions_misc_file-types.md":"07286efe","extensions_misc_icons_index.md":"8c18385c","extensions_misc_pack-types.md":"90ff532b","extensions_presets_index.md":"cf7a3e9a","extensions_presets_manifest_index.md":"bfeefdf7","extensions_presets_preset-scripts.md":"610b2759","extensions_publishing_components-and-commands.md":"3c822f67","extensions_publishing_index.md":"64eed42e","extensions_scripts_index.md":"6d820e70","extensions_snippets_documentation.md":"d01c53f6","extensions_snippets_index.md":"9ddd55cd","guide_advanced_custom-commands_index.md":"c7a26261","guide_advanced_custom-components_index.md":"9b47d27c","guide_advanced_dash_index.md":"272afd57","guide_advanced_generator-scripts_index.md":"c082dc0c","guide_advanced_molang-ast-scripts_index.md":"e73eb485","guide_advanced_molang-files_index.md":"572c9ffb","guide_community.md":"6675d974","guide_download_index.md":"36f85fc2","guide_faq_index.md":"7740b849","guide_features_index.md":"6f03c3ee","guide_index.md":"1d2a62e9","guide_migration-guide_index.md":"7f2c23c0","guide_misc_com-mojang-syncing_index.md":"80e6e63c","guide_misc_export-project_index.md":"28d62489","guide_misc_import-project.md":"f1cafa85","guide_misc_project-config.md":"0e827338","guide_misc_project-types_index.md":"8b9e0a25","guide_why-bridge.md":"4978a065","index.md":"cb02ac93","team.md":"88f0c1d0"}
